django_db_xlsx/__init__.py
django_db_xlsx/util.py
django_db_xlsx/tests/__init__.py
django_db_xlsx/tests/test_dbz.py
django_db_xlsx-1.0.1.dist-info/DESCRIPTION.rst
django_db_xlsx-1.0.1.dist-info/METADATA
django_db_xlsx-1.0.1.dist-info/RECORD
django_db_xlsx-1.0.1.dist-info/WHEEL
django_db_xlsx-1.0.1.dist-info/metadata.json
django_db_xlsx-1.0.1.dist-info/top_level.txt
