Metadata-Version: 2.0
Name: django-db-xlsx
Version: 1.0.1
Summary: Import/export django models via xlsx
Home-page: https://github.com/narfman0/django-db-xlsx
Author: Jon Robison
Author-email: narfman0@gmail.com
License: MIT
Keywords: django,database,xlsx
Platform: UNKNOWN
Classifier: Development Status :: 4 - Beta
Classifier: Framework :: Django
Classifier: Framework :: Django :: 1.8
Classifier: Framework :: Django :: 1.9
Classifier: Framework :: Django :: 1.10
Classifier: Intended Audience :: Developers
Classifier: License :: OSI Approved :: BSD License
Classifier: Natural Language :: English
Classifier: Programming Language :: Python :: 2
Classifier: Programming Language :: Python :: 2.7
Classifier: Programming Language :: Python :: 3
Classifier: Programming Language :: Python :: 3.5
Requires-Dist: django
Requires-Dist: openpyxl
